[{"TITLE": " SUPPLY CHAIN MGMT", "CREDIT": "3.0", "SECTION": [{"section": "A", "seats": "0", "times": "M W F 8:00am-8:50am"}, {"section": "B", "seats": "0", "times": "M W F 9:00am-9:50am"}, {"section": "C", "seats": "0", "times": "T R 3:40pm-5:00pm"}, {"section": "F", "seats": "0", "times": "M W 2:10pm-3:00pm"}, {"section": "G", "seats": "0", "times": "M W F 3:10pm-4:00pm"}, {"section": "J", "seats": "0", "times": "T R 12:40pm-2:00pm"}, {"section": "K", "seats": "0", "times": "T R 8:00am-9:15am"}, {"section": "L", "seats": "0", "times": "T R 2:10pm-3:25pm"}, {"section": "", "seats": "232", "times": "M M W F 12:10pm-1:00pm M"}, {"section": "P", "seats": "19", "times": "T R 5:10pm-6:25pm"}, {"section": "Q", "seats": "39", "times": "T R 6:40pm-7:55pm"}], "PREREQ": " ECON 101, STAT 226", "NOTE": " Night Exams Scheduled", "COURSE": "301"}, {"TITLE": " PROJECT MANAGEMENT", "CREDIT": "3.0", "SECTION": [{"section": "A1", "seats": "0", "times": "T R 2:10pm-3:25pm M"}, {"section": "A2", "seats": "0", "times": "T R 2:10pm-3:25pm M"}, {"section": "B1", "seats": "0", "times": "T R 12:40pm-2:00pm M"}, {"section": "B2", "seats": "0", "times": "T R 12:40pm-2:00pm M"}, {"section": "C1", "seats": "23", "times": "M 6:40pm-9:25pm"}, {"section": "C2", "seats": "8", "times": "M 6:40pm-9:25pm"}], "PREREQ": " CREDIT OR ENROLLMENT IN MIS 301", "NOTE": " SECTNS A1,B1,C1 RESTRICTED TO ACCT, BUS U, BUSEC,FIN, LSCM, MGMT, MIS, MKT, OSCM, SCM UNDERGRAD MAJORSONLY. SECTIONS A2,B2,C2 RESTRICTED TO COLLEGES OTHERTHAN BUSINESS.", "COURSE": "340"}, {"TITLE": " MFG PLANNING&CONTRL", "CREDIT": "3.0", "SECTION": [{"section": "A1", "seats": "0", "times": "T R 2:10pm-3:25pm"}, {"section": "A2", "seats": "0", "times": "T R 2:10pm-3:25pm"}], "PREREQ": " SCM 301", "NOTE": " GRADUATE STUDENTS GO TO 1200 GERDIN FORPERMISSION TO ADD", "COURSE": "422"}, {"TITLE": " PROCSS MGT,AN&IMPRV", "CREDIT": "3.0", "SECTION": [{"section": "A", "seats": "0", "times": "T R 11:00am-12:15pm"}, {"section": "B", "seats": "18", "times": "T R 3:40pm-5:00pm"}], "PREREQ": " SCM 301", "NOTE": " COURSE RESTRICTED TO ACCT, BUS S, BUS U, FIN,LSCM, MGMT, MIS, MKT, OSCM, SCM UNDERGRAD MAJORS.GRADUATE STUDENTS GO TO 1200 GERDIN FOR PERMISSIONTO ADD.", "COURSE": "424"}, {"PREREQ": " MIS 330, SCM 301", "COURSE": "440", "SECTION": [{"section": "A1", "seats": "0", "times": "T R 8:00am-9:15am"}, {"section": "A2", "seats": "0", "times": "T R 8:00am-9:15am"}], "CREDIT": "3.0", "TITLE": " SUPLY CHAIN INFO SY"}, {"TITLE": " DECISN TOOLS LOG&OP", "CREDIT": "3.0", "SECTION": [{"section": "A1", "seats": "9", "times": "M W F 9:00am-9:50am"}, {"section": "A2", "seats": "4", "times": "M W F 9:00am-9:50am"}, {"section": "B1", "seats": "0", "times": "M W F 10:00am-10:50am"}, {"section": "B2", "seats": "2", "times": "M W F 10:00am-10:50am"}], "PREREQ": " SCM 301", "NOTE": " SECTNS A1,B1 RESTRICTED TO COLLEGE OF BUSINESSUNDERGRAD MAJORS ONLY. SECTIONS A2,B2 RESTRICTED TOCOLLEGES OTHER THAN BUSINESS. COURSE NOT OPEN TOP BUS. GRADUATE STUDENTS GO TO 1200 GERDIN FORPERMISSION TO ADD.", "COURSE": "460"}, {"TITLE": " PRIN TRANSPORTATION", "CREDIT": "3.0", "SECTION": [{"section": "B1", "seats": "0", "times": "M W F 12:10pm-1:00pm"}, {"section": "B2", "seats": "0", "times": "M W F 12:10pm-1:00pm"}], "PREREQ": " SCM 301", "NOTE": " GRADUATE STUDENTS GO TO 1200 GERDIN FORPERMISSION TO ADD", "COURSE": "461"}, {"PREREQ": " CREDIT OR ENROLLMENT IN SCM 461", "COURSE": "462", "SECTION": [{"section": "A1", "seats": "28", "times": "T R 12:40pm-2:00pm"}, {"section": "A2", "seats": "4", "times": "T R 12:40pm-2:00pm"}], "CREDIT": "3.0", "TITLE": " TRANSPO CARRIER MGT"}, {"TITLE": " DEMAND PLANNING&MGT", "CREDIT": "3.0", "SECTION": [{"section": "A", "seats": "0", "times": "M W F 8:00am-8:50am"}, {"section": "B", "seats": "0", "times": "M W F 9:00am-9:50am"}], "PREREQ": " SCM 301", "NOTE": " COURSE RESTRICTED TO ACCT, BUS S, BUS U,BUSEC, FIN, LSCM, MGMT, MIS, MKT, OSCM, SCM UNDERGRADMAJORS ONLY. GRADUATE STUDENTS GO TO 1200 GERDINFOR PERMISSION TO ADD.", "COURSE": "485"}, {"TITLE": " PRIN PRCHS&SPLY MGT", "CREDIT": "3.0", "SECTION": [{"section": "A", "seats": "9", "times": "T R 12:40pm-2:00pm"}, {"section": "B", "seats": "0", "times": "T R 9:30am-10:45am"}], "PREREQ": " SCM 301", "NOTE": " COURSE RESTRICTED TO ACCT, BUS S, BUS U,BUSEC, FIN, LSCM, MGMT, MIS, MKT, OSCM, SCM UNDERGRADMAJORS ONLY. GRADUATE STUDENTS GO TO 1200 GERDINFOR PERMISSION TO ADD.", "COURSE": "486"}, {"TITLE": " STRTGC SPLY CHN MGT", "CREDIT": "3.0", "SECTION": [{"section": "B", "seats": "17", "times": "M W F 1:10pm-2:00pm"}], "PREREQ": " SCM 460 OR SCM 422 OR SCM 424; SCM 485 ORSCM 486", "NOTE": " COURSE RESTRICTED TO LSCM, OSCM, SCM SENIORSGRADUATING FALL 2014. GRADUATE STUDENTS GO TO1200 GERDIN FOR PERMISSION TO ADD.", "COURSE": "487"}, {"TITLE": " INDEPENDENT STUDY", "CREDIT": "1.0-3.0", "SECTION": [{"section": "", "seats": "0", "times": ""}], "PREREQ": " SCM 301, SENIOR CLASSIFICATN, INSTRUCTORPERMISSION", "NOTE": " Department permission required.", "COURSE": "490"}, {"TITLE": " PURCHASI&SUPPLY MGT", "CREDIT": "3.0", "SECTION": [{"section": "B", "seats": "4", "times": "M 6:00pm-9:20pm"}], "PREREQ": " SCM 501 OR PERMISSION OF INSTRUCTOR", "NOTE": " RESTRICTED TO BUSINESS COLLEGE GRADUATE STUDENTS", "COURSE": "563"}, {"TITLE": " SPECIAL TOPICS", "CREDIT": "1.0-3.0", "SECTION": [{"section": "", "seats": "0", "times": ""}], "PREREQ": " GRAD CLASSIFICATION, INSTRUCTOR PERMISSN", "NOTE": " RESTRICTED TO BUSINESS COLLEGE GRADUATE STUDENTS", "COURSE": "590"}, {"TITLE": " THEOR FOUNDATNS SCM", "CREDIT": "3.0", "SECTION": [{"section": "A", "seats": "7", "times": "W 2:10pm-5:00pm"}], "PREREQ": " MGMT 601 OR PERMISSION OF INSTRUCTOR", "NOTE": " MUST BE A BUSINESS PH.D. STUDENT, OR HAVEDEPARTMENTAL PERMISSION", "COURSE": "601"}, {"TITLE": " RSEARCH PRACTICUM I", "CREDIT": "1.0", "SECTION": [{"section": "", "seats": "0", "times": ""}], "PREREQ": " ENROLLMENT IN THE PH D PROGRAM", "NOTE": " MUST BE A BUSAD PH.D. STUDENT, OR HAVEDEPARTMENTAL PERMISSION", "COURSE": "650"}, {"TITLE": " RSEARCH PRACTICM II", "CREDIT": "1.0", "SECTION": [{"section": "", "seats": "0", "times": ""}], "PREREQ": " ENROLLMENT IN THE PH D PROGRAM", "NOTE": " MUST BE A BUSAD PH.D. STUDENT, OR HAVEDEPARTMENTAL PERMISSION", "COURSE": "651"}]