[{"TITLE": " EXCEPTIONAL LEARNER", "CREDIT": "3.0", "SECTION": [{"section": "1", "seats": "163", "times": "M W F 9:00am-9:50am"}], "PREREQ": " C I 204", "NOTE": " Meets U.S. Diversity ReqmtDepartment permission required 1st week.", "COURSE": "250"}, {"TITLE": " INTR INST MI/M DSAB", "CREDIT": "3.0", "SECTION": [{"section": "", "seats": "13", "times": "T R 2:10pm-3:25pm"}], "PREREQ": " SP ED 250, CONCURRENT ENROLLMENT INC I 280I, C I 377", "NOTE": " Department permission required 1st week.", "COURSE": "330"}, {"TITLE": " EXCEP LRN GEN CLASS", "CREDIT": "3.0", "SECTION": [{"section": "1", "seats": "13", "times": "T R 3:40pm-5:00pm"}], "PREREQ": " CONCURRENT ENROLLMENT IN SP ED 330", "NOTE": " Department permission required 1st week.", "COURSE": "334"}, {"PREREQ": " C I 433, C I 439, C I 468I;CONCURRENT ENROLLMENT IN SP ED 455", "COURSE": "355", "SECTION": [{"section": "NO", "seats": "6", "times": "M W 10:45am-12:00pm"}], "CREDIT": "2.0", "TITLE": " ASESS INCLUSV CLSRM"}, {"TITLE": " TCHG IN INCLUSV SET", "CREDIT": "1.0", "SECTION": [{"section": "2", "seats": "3", "times": "W 8:00am-9:15am"}], "PREREQ": " CONCURRENT ENROLLMENT IN C I 377,C I 438, C I 468F, C I 468G", "NOTE": " CONCURRENT ENROLLMENT IN C I 377, 438 AND 468FREQUIRED", "COURSE": "368"}, {"COURSE": "401", "SECTION": [{"section": "", "seats": "20", "times": "T R 8:00am-9:15am"}], "CREDIT": "3.0", "TITLE": " TCH SCDRY EXCEP GEN"}, {"TITLE": " SUPV STUDENT TEACHG", "CREDIT": "1.0-30.0", "SECTION": [{"section": "", "seats": "0", "times": ""}], "PREREQ": " FULL ADMISSION TO TEACHER EDUC, SENIORCLASSIFICATION, MAJOR IN ELEMENTARY EDUC, SP ED 330,SP ED 334, SP ED 365, SP ED 436, SP ED 439,C I 280I, C I 452", "NOTE": " COURSE RESTRICTED TO EL ED MAJORS WITH FULLOR TENTATIVE ADMISSION TO THE UNIVERSITY TEACHEREDUCATION PROGRAMDepartment permission required 1st week.", "COURSE": "416"}, {"PREREQ": " C I 433, C I 439, C I 468I, CONCURRENTENROLLMENT SP ED 355", "COURSE": "455", "SECTION": [{"section": "NO", "seats": "7", "times": "M W 12:30pm-1:45pm"}], "CREDIT": "2.0", "TITLE": " INSTR MTH INCLU PRI"}, {"TITLE": " PRE-TCHG III:M DSBL", "CREDIT": "1.0", "SECTION": [{"section": "", "seats": "5", "times": ""}], "PREREQ": " SP ED 330, SP ED 339, SP ED 365,SP ED 436; ADMISSION TO UNIVERSITY TEACHER ED PROGRAM", "NOTE": " Satisfactory/Fail Only", "COURSE": "459"}, {"PREREQ": " SP ED 436 AND CONCURRENT ENROLLMENTIN SP ED 459", "COURSE": "460", "SECTION": [{"section": "", "seats": "0", "times": "R 11:00am-11:50am"}], "CREDIT": "1.0", "TITLE": " SPECIAL ED SEMINAR"}, {"PREREQ": " SP ED 365, SP ED 436", "COURSE": "464", "SECTION": [{"section": "2", "seats": "3", "times": "W 5:10pm-8:00pm"}], "CREDIT": "3.0", "TITLE": " COLLAB PARTNERSHIPS"}, {"TITLE": " INDEPENDENT STUDY", "CREDIT": "1.0-5.0", "SECTION": [{"section": "", "seats": "0", "times": ""}], "PREREQ": " 12 CR IN EL ED, PERMISSION OF DEPT CHAIR", "NOTE": " Department permission required 1st week.", "COURSE": "490"}, {"PREREQ": " RESEV 550, SP ED 515", "COURSE": "517", "SECTION": [{"section": "1", "seats": "3", "times": ""}], "CREDIT": "2.0", "TITLE": " RESEARCH REVIEW"}, {"PREREQ": " 15 CRS IN EDUC; PERMISSION OF DEPT CHAIR", "COURSE": "590", "SECTION": [{"section": "", "seats": "0", "times": ""}], "CREDIT": "1.0-5.0", "TITLE": " SPECIAL TOPICS"}, {"TITLE": " FLD EXP BHV/DS,5-21", "CREDIT": "1.0-6.0", "SECTION": [{"section": "", "seats": "0", "times": ""}], "PREREQ": " 15 GRAD CREDITS IN SPECIAL AREA;ADMISSION TO GRAD PROGRAM IN SPECIAL EDUCATION", "NOTE": " COURSE RESTRICTED TO C I MAJORS ONLY", "COURSE": "591K"}, {"PREREQ": " 15 CREDITS IN EDUCATION", "COURSE": "599", "SECTION": [{"section": "", "seats": "0", "times": ""}], "CREDIT": "1.0-5.0", "TITLE": " CREATIVE COMPONENT"}, {"PREREQ": " 15 CREDITS IN EDUCATION", "COURSE": "699", "SECTION": [{"section": "", "seats": "0", "times": ""}], "CREDIT": "1.0-30.0", "TITLE": " RESEARCH"}]